LICENSE
MANIFEST.in
README.md
requirements.txt
setup.cfg
setup.py
pyrecsys/__init__.py
pyrecsys/collaborative_filtering.py
pyrecsys.egg-info/PKG-INFO
pyrecsys.egg-info/SOURCES.txt
pyrecsys.egg-info/dependency_links.txt
pyrecsys.egg-info/requires.txt
pyrecsys.egg-info/top_level.txt
pyrecsys/_polara/lib/__init__.py
pyrecsys/_polara/lib/hosvd.py