Metadata-Version: 1.0
Name: pyrecsys
Version: 0.0.3
Summary: Collaborative filtering recommender system
Home-page: https://github.com/vlarine/pyrecsys
Author: Vladimir Larin
Author-email: vladimir@vlarine.ru
License: MIT
Platform: UNKNOWN
